README.md
setup.py
pyveasy.egg-info/PKG-INFO
pyveasy.egg-info/SOURCES.txt
pyveasy.egg-info/dependency_links.txt
pyveasy.egg-info/entry_points.txt
pyveasy.egg-info/requires.txt
pyveasy.egg-info/top_level.txt
src/__init__.py
src/main.py