Metadata-Version: 2.1
Name: pyveasy
Version: 1.6.0
Summary: PyEasy is a project generator for bootstrapping basic Python to VSCode.
Home-page: https://pypi.org/project/pyveasy/
Author: Anderson Braz de Sousa
Author-email: contato@andersonbraz.com
License: UNKNOWN
Platform: UNKNOWN
Classifier: Programming Language :: Python :: 3
Classifier: License :: OSI Approved :: MIT License
Requires-Python: >=3.6
